qiipy/__init__.py
qiipy/client.py
qiipy/comment.py
qiipy/exception.py
qiipy/group.py
qiipy/group_member.py
qiipy/item.py
qiipy/member.py
qiipy/project.py
qiipy/reaction.py
qiipy/route.py
qiipy/session.py
qiipy/tag.py
qiipy/tagging.py
qiipy/team.py
qiipy/team_member.py
qiipy/template.py
qiipy/test.py
qiipy/user.py
pyqiita-1.1.0.dist-info/LICENSE
pyqiita-1.1.0.dist-info/METADATA
pyqiita-1.1.0.dist-info/WHEEL
pyqiita-1.1.0.dist-info/top_level.txt
pyqiita-1.1.0.dist-info/RECORD
