Metadata-Version: 2.1
Name: pyqiita
Version: 1.1.0
Summary: An API wrapper for Qiita.
Home-page: https://github.com/peco2282/Qiipy
Author: peco2282
Author-email: pecop2282@gmail.com
License: MIT
License-File: LICENSE
Requires-Dist: requests
